pycritty/__init__.py
pycritty/main.py
pycritty/api/__init__.py
pycritty/api/config.py
pycritty/api/install.py
pycritty/api/load.py
pycritty/api/ls.py
pycritty/api/rm.py
pycritty/api/save.py
pycritty/cli/__init__.py
pycritty/cli/cli.py
pycritty/cli/install.py
pycritty/cli/load.py
pycritty/cli/ls.py
pycritty/cli/pycritty.py
pycritty/cli/rm.py
pycritty/cli/save.py
pycritty/io/__init__.py
pycritty/io/log.py
pycritty/io/yaml_io.py
pycritty/resources/__init__.py
pycritty/resources/resource.py
pycritty-0.4.0.dist-info/LICENSE
pycritty-0.4.0.dist-info/METADATA
pycritty-0.4.0.dist-info/WHEEL
pycritty-0.4.0.dist-info/entry_points.txt
pycritty-0.4.0.dist-info/top_level.txt
pycritty-0.4.0.dist-info/RECORD
