Metadata-Version: 2.1
Name: pycritty
Version: 0.4.0
Summary: CLI program that allows you to change your alacritty config file with one command.
Home-page: https://github.com/antoniosarosi/pycritty
Author: Antonio Sarosi
Author-email: sarosiantonio@gmail.com
License: UNKNOWN
Keywords: alacritty
Platform: UNKNOWN
Classifier: Programming Language :: Python :: 3
Classifier: License :: OSI Approved :: MIT License
Classifier: Operating System :: POSIX :: Linux
Classifier: Topic :: Terminals :: Terminal Emulators/X Terminals
Requires-Python: >=3.6
License-File: LICENSE
Requires-Dist: PyYAML
